unify/__init__.py
unify/assistants/__init__.py
unify/assistants/management.py
unify/logging/__init__.py
unify/logging/dataset.py
unify/logging/logs.py
unify/logging/utils/__init__.py
unify/logging/utils/async_logger.py
unify/logging/utils/compositions.py
unify/logging/utils/contexts.py
unify/logging/utils/datasets.py
unify/logging/utils/logs.py
unify/logging/utils/projects.py
unify/logging/utils/tracing.py
unify/universal_api/__init__.py
unify/universal_api/casting.py
unify/universal_api/chatbot.py
unify/universal_api/clients/__init__.py
unify/universal_api/clients/base.py
unify/universal_api/clients/helpers.py
unify/universal_api/clients/multi_llm.py
unify/universal_api/clients/uni_llm.py
unify/universal_api/endpoints/__init__.py
unify/universal_api/endpoints/anthropic.py
unify/universal_api/endpoints/bedrock.py
unify/universal_api/endpoints/deepseek.py
unify/universal_api/endpoints/groq.py
unify/universal_api/endpoints/mistral.py
unify/universal_api/endpoints/openai.py
unify/universal_api/endpoints/replicate.py
unify/universal_api/endpoints/togetherai.py
unify/universal_api/endpoints/utils.py
unify/universal_api/endpoints/vertexai.py
unify/universal_api/endpoints/xai.py
unify/universal_api/types/__init__.py
unify/universal_api/types/prompt.py
unify/universal_api/usage.py
unify/universal_api/utils/__init__.py
unify/universal_api/utils/credits.py
unify/universal_api/utils/custom_api_keys.py
unify/universal_api/utils/custom_endpoints.py
unify/universal_api/utils/httpx_logging.py
unify/universal_api/utils/provider_preprocessing.py
unify/universal_api/utils/queries.py
unify/universal_api/utils/supported_endpoints.py
unify/universal_api/utils/user.py
unify/utils/__init__.py
unify/utils/_caching.py
unify/utils/caching/__init__.py
unify/utils/caching/base_cache.py
unify/utils/caching/cache_benchmark.py
unify/utils/caching/local_cache.py
unify/utils/caching/local_separate_cache.py
unify/utils/caching/ndsjson_cache_utils.py
unify/utils/caching/remote_cache.py
unifyai-0.9.159.dist-info/METADATA
unifyai-0.9.159.dist-info/WHEEL
unifyai-0.9.159.dist-info/licenses/LICENSE
unifyai-0.9.159.dist-info/RECORD
