Metadata-Version: 2.4
Name: unifyai
Version: 0.9.159
Summary: A Python package for interacting with the Unify API
License-File: LICENSE
Author: Unify
Author-email: hello@unify.com
Requires-Python: >=3.10,<4.0
Classifier: Programming Language :: Python :: 3
Classifier: Programming Language :: Python :: 3.10
Classifier: Programming Language :: Python :: 3.11
Classifier: Programming Language :: Python :: 3.12
Classifier: Programming Language :: Python :: 3.13
Classifier: Programming Language :: Python :: 3.14
Requires-Dist: aiohttp (>=3.11.12,<4.0.0)
Requires-Dist: google-genai (>=1.52.0,<2.0.0)
Requires-Dist: jsonlines (>=3.1.0,<4.0.0)
Requires-Dist: litellm (>=1.80.7,<2.0.0)
Requires-Dist: openai (>=2.8.1,<3.0.0)
Requires-Dist: pytest (>=8.3.3,<9.0.0)
Requires-Dist: pytest-asyncio (>=0.24.0)
Requires-Dist: pytest-timeout (>=2.3.1,<3.0.0)
Requires-Dist: requests (>=2.31.0,<3.0.0)
Requires-Dist: requests-toolbelt (>=1.0.0,<2.0.0)
Requires-Dist: rich (>=13.8.1,<14.0.0)
Requires-Dist: termcolor (==2.5.0)
Project-URL: Repository, https://github.com/unifyai/unify
